{
	"info": {
		"_postman_id": "4657d520-8e3c-4ce9-baea-b1173ea4eeab",
		"name": "LINE-PUSH",
		"schema": "https://schema.getpostman.com/json/collection/v2.1.0/collection.json",
		"_exporter_id": "17861619",
		"_collection_link": "https://restless-firefly-378967.postman.co/workspace/pakgon-api-v2~0b23999a-6ef1-4560-99c2-fbf17da49518/collection/17861619-4657d520-8e3c-4ce9-baea-b1173ea4eeab?action=share&source=collection_link&creator=17861619"
	},
	"item": [
		{
			"name": "push-message-flex",
			"request": {
				"auth": {
					"type": "bearer",
					"bearer": [
						{
							"key": "token",
							"value": "e1l7kAgUdMdDoCmJs3xyDu0R1yXIGedLufWKFYcAGQjgERyrPzImX6w14qLAXKWC/ZHsPuaRNR84k4V03tn0ZakqxVCLdTwChapiTEn1NnnW1nfvqhDlx0KFHMk8wRUXuFoeFZy5NlcnTpEKGT3hdAdB04t89/1O/w1cDnyilFU=",
							"type": "string"
						}
					]
				},
				"method": "POST",
				"header": [],
				"body": {
					"mode": "raw",
					"raw": "{\n    \"to\": \"U1fb08bc0ba902ecfbafc313b9092ede6\",\n    \"messages\": [\n        {\n            \"type\": \"flex\",\n            \"altText\": \"🏥 ข้อมูล: กรมควบคุมโรค(สายด่วน1422)\",\n            \"contents\": {\n                \"type\": \"bubble\",\n                \"hero\": {\n                    \"type\": \"image\",\n                    \"url\": \"https://scdn.line-apps.com/n/channel_devcenter/img/fx/01_1_cafe.png\",\n                    \"size\": \"full\",\n                    \"aspectRatio\": \"20:13\",\n                    \"aspectMode\": \"cover\",\n                    \"action\": {\n                        \"type\": \"uri\",\n                        \"label\": \"Line\",\n                        \"uri\": \"https://linecorp.com/\"\n                    }\n                },\n                \"body\": {\n                    \"type\": \"box\",\n                    \"layout\": \"vertical\",\n                    \"contents\": [\n                        {\n                            \"type\": \"text\",\n                            \"text\": \"Brown Cafe\",\n                            \"weight\": \"bold\",\n                            \"size\": \"xl\",\n                            \"contents\": []\n                        },\n                        {\n                            \"type\": \"box\",\n                            \"layout\": \"baseline\",\n                            \"margin\": \"md\",\n                            \"contents\": [\n                                {\n                                    \"type\": \"icon\",\n                                    \"url\": \"https://scdn.line-apps.com/n/channel_devcenter/img/fx/review_gold_star_28.png\",\n                                    \"size\": \"sm\"\n                                },\n                                {\n                                    \"type\": \"icon\",\n                                    \"url\": \"https://scdn.line-apps.com/n/channel_devcenter/img/fx/review_gold_star_28.png\",\n                                    \"size\": \"sm\"\n                                },\n                                {\n                                    \"type\": \"icon\",\n                                    \"url\": \"https://scdn.line-apps.com/n/channel_devcenter/img/fx/review_gold_star_28.png\",\n                                    \"size\": \"sm\"\n                                },\n                                {\n                                    \"type\": \"icon\",\n                                    \"url\": \"https://scdn.line-apps.com/n/channel_devcenter/img/fx/review_gold_star_28.png\",\n                                    \"size\": \"sm\"\n                                },\n                                {\n                                    \"type\": \"icon\",\n                                    \"url\": \"https://scdn.line-apps.com/n/channel_devcenter/img/fx/review_gray_star_28.png\",\n                                    \"size\": \"sm\"\n                                },\n                                {\n                                    \"type\": \"text\",\n                                    \"text\": \"4.0\",\n                                    \"size\": \"sm\",\n                                    \"color\": \"#999999\",\n                                    \"flex\": 0,\n                                    \"margin\": \"md\",\n                                    \"contents\": []\n                                }\n                            ]\n                        },\n                        {\n                            \"type\": \"box\",\n                            \"layout\": \"vertical\",\n                            \"spacing\": \"sm\",\n                            \"margin\": \"lg\",\n                            \"contents\": [\n                                {\n                                    \"type\": \"box\",\n                                    \"layout\": \"baseline\",\n                                    \"spacing\": \"sm\",\n                                    \"contents\": [\n                                        {\n                                            \"type\": \"text\",\n                                            \"text\": \"Place\",\n                                            \"size\": \"sm\",\n                                            \"color\": \"#AAAAAA\",\n                                            \"flex\": 1,\n                                            \"contents\": []\n                                        },\n                                        {\n                                            \"type\": \"text\",\n                                            \"text\": \"Miraina Tower, 4-1-6 Shinjuku, Tokyo\",\n                                            \"size\": \"sm\",\n                                            \"color\": \"#666666\",\n                                            \"flex\": 5,\n                                            \"wrap\": true,\n                                            \"contents\": []\n                                        }\n                                    ]\n                                },\n                                {\n                                    \"type\": \"box\",\n                                    \"layout\": \"baseline\",\n                                    \"spacing\": \"sm\",\n                                    \"contents\": [\n                                        {\n                                            \"type\": \"text\",\n                                            \"text\": \"Time\",\n                                            \"size\": \"sm\",\n                                            \"color\": \"#AAAAAA\",\n                                            \"flex\": 1,\n                                            \"contents\": []\n                                        },\n                                        {\n                                            \"type\": \"text\",\n                                            \"text\": \"10:00 - 23:00\",\n                                            \"size\": \"sm\",\n                                            \"color\": \"#666666\",\n                                            \"flex\": 5,\n                                            \"wrap\": true,\n                                            \"contents\": []\n                                        }\n                                    ]\n                                }\n                            ]\n                        }\n                    ]\n                },\n                \"footer\": {\n                    \"type\": \"box\",\n                    \"layout\": \"vertical\",\n                    \"flex\": 0,\n                    \"spacing\": \"sm\",\n                    \"contents\": [\n                        {\n                            \"type\": \"button\",\n                            \"action\": {\n                                \"type\": \"uri\",\n                                \"label\": \"CALL\",\n                                \"uri\": \"https://linecorp.com\"\n                            },\n                            \"height\": \"sm\",\n                            \"style\": \"link\"\n                        },\n                        {\n                            \"type\": \"button\",\n                            \"action\": {\n                                \"type\": \"uri\",\n                                \"label\": \"WEBSITE\",\n                                \"uri\": \"https://linecorp.com\"\n                            },\n                            \"height\": \"sm\",\n                            \"style\": \"link\"\n                        },\n                        {\n                            \"type\": \"spacer\",\n                            \"size\": \"sm\"\n                        }\n                    ]\n                }\n            }\n        }\n    ]\n}",
					"options": {
						"raw": {
							"language": "json"
						}
					}
				},
				"url": {
					"raw": "https://api.line.me/v2/bot/message/push",
					"protocol": "https",
					"host": [
						"api",
						"line",
						"me"
					],
					"path": [
						"v2",
						"bot",
						"message",
						"push"
					]
				}
			},
			"response": [
				{
					"name": "push-message-flex",
					"originalRequest": {
						"method": "POST",
						"header": [],
						"body": {
							"mode": "raw",
							"raw": "{\n    \"to\": \"Cf10f0f99bce53218fdaff62cecb5ea48\",\n    \"messages\": [{\n        \"type\": \"flex\",\n            \"altText\": \"🏥 ข้อมูล: กรมควบคุมโรค(สายด่วน1422)\",\n            \"contents\": {\n    }]\n}",
							"options": {
								"raw": {
									"language": "json"
								}
							}
						},
						"url": {
							"raw": "https://api.line.me/v2/bot/message/push",
							"protocol": "https",
							"host": [
								"api",
								"line",
								"me"
							],
							"path": [
								"v2",
								"bot",
								"message",
								"push"
							]
						}
					},
					"_postman_previewlanguage": null,
					"header": null,
					"cookie": [],
					"body": null
				}
			]
		},
		{
			"name": "push-message-text",
			"request": {
				"auth": {
					"type": "bearer",
					"bearer": [
						{
							"key": "token",
							"value": "e1l7kAgUdMdDoCmJs3xyDu0R1yXIGedLufWKFYcAGQjgERyrPzImX6w14qLAXKWC/ZHsPuaRNR84k4V03tn0ZakqxVCLdTwChapiTEn1NnnW1nfvqhDlx0KFHMk8wRUXuFoeFZy5NlcnTpEKGT3hdAdB04t89/1O/w1cDnyilFU=",
							"type": "string"
						}
					]
				},
				"method": "POST",
				"header": [],
				"body": {
					"mode": "raw",
					"raw": "{\n    \"to\": \"U1fb08bc0ba902ecfbafc313b9092ede6\",\n    \"messages\": [\n        {\n            \"type\": \"text\",\n            \"text\": \"tesssst\"\n        }\n    ]\n}",
					"options": {
						"raw": {
							"language": "json"
						}
					}
				},
				"url": {
					"raw": "https://api.line.me/v2/bot/message/push",
					"protocol": "https",
					"host": [
						"api",
						"line",
						"me"
					],
					"path": [
						"v2",
						"bot",
						"message",
						"push"
					]
				}
			},
			"response": []
		},
		{
			"name": "webhook",
			"request": {
				"auth": {
					"type": "bearer",
					"bearer": [
						{
							"key": "token",
							"value": "e1l7kAgUdMdDoCmJs3xyDu0R1yXIGedLufWKFYcAGQjgERyrPzImX6w14qLAXKWC/ZHsPuaRNR84k4V03tn0ZakqxVCLdTwChapiTEn1NnnW1nfvqhDlx0KFHMk8wRUXuFoeFZy5NlcnTpEKGT3hdAdB04t89/1O/w1cDnyilFU=",
							"type": "string"
						}
					]
				},
				"method": "GET",
				"header": [],
				"url": {
					"raw": "http://localhost:3000/",
					"protocol": "http",
					"host": [
						"localhost"
					],
					"port": "3000",
					"path": [
						""
					]
				}
			},
			"response": []
		},
		{
			"name": "create-user",
			"request": {
				"method": "POST",
				"header": [],
				"body": {
					"mode": "raw",
					"raw": "{\n    \"userId\": \"U1fb08bc0ba902ecfbafc313b9092ede6\",\n    \"displayName\": \"Nack\",\n    \"statusMessage\": \"Software Development\\n\\n063-674-9204\",\n    \"pictureUrl\": \"https://profile.line-scdn.net/0ha-CG4_dEPgJuPi5jKGxAfR5uPWhNT2cQRll5Y1k7ZTdRXXADFgskZ1hpYjRQXXoEQgwhYl08MDZiLUlkcGjCNmkOYzNSCn5USllx4A\"\n}",
					"options": {
						"raw": {
							"language": "json"
						}
					}
				},
				"url": {
					"raw": "http://localhost:3000/user/create-user",
					"protocol": "http",
					"host": [
						"localhost"
					],
					"port": "3000",
					"path": [
						"user",
						"create-user"
					]
				}
			},
			"response": []
		},
		{
			"name": "getAll",
			"protocolProfileBehavior": {
				"disableBodyPruning": true
			},
			"request": {
				"method": "GET",
				"header": [],
				"body": {
					"mode": "raw",
					"raw": "{\n    \"userId\": \"U1fb08bc0ba902ecfbafc313b9092ede6\",\n    \"displayName\": \"Nack\",\n    \"statusMessage\": \"Software Development\\n\\n063-674-9204\",\n    \"pictureUrl\": \"https://profile.line-scdn.net/0ha-CG4_dEPgJuPi5jKGxAfR5uPWhNT2cQRll5Y1k7ZTdRXXADFgskZ1hpYjRQXXoEQgwhYl08MDZiLUlkcGjCNmkOYzNSCn5USllx4A\"\n}",
					"options": {
						"raw": {
							"language": "json"
						}
					}
				},
				"url": {
					"raw": "http://localhost:3000/user/getAll",
					"protocol": "http",
					"host": [
						"localhost"
					],
					"port": "3000",
					"path": [
						"user",
						"getAll"
					]
				}
			},
			"response": []
		}
	]
}